{
  "notified": {
    "SALAM-UTAMA-INDI": {
      "NBS-Rohadi": "2026-01-08T03:33:00.106Z"
    },
    "SALAM-UTAMA-METRO": {
      "SLM-Budi Nurwanta": "2026-01-08T02:19:30.237Z",
      "SLM-Ika Setiyawati": "2026-01-08T02:19:30.237Z",
      "WDK-Eko Haryanto": "2026-01-08T05:27:30.303Z",
      "SLM-Arip": "2026-01-08T06:06:30.346Z",
      "WDK-Didik": "2026-01-08T06:06:30.346Z"
    }
  },
  "lastReports": {
    "13:22": "2025-12-11T06:22:01.068Z",
    "10:11": "2025-12-12T03:11:01.355Z",
    "10:38": "2025-12-12T03:38:02.675Z"
  },
  "threshold": {
    "minMinutes": 3,
    "maxMinutes": 300
  },
  "scheduleTimes": [
    "07:00",
    "15:00"
  ],
  "notificationDelayMs": 30000
}